Workbook

Sheet Sheet1
A1: Salesfunnel Zenvoices (GEREALISEERD) | H1: AANNAME | I1: IN TE VULLEN | L1: SEA | M1: Op basis van linkedin data
L2: MAX Cost per view | M2: =B13*B11*M3 -> 6.3068981 | N2: - | O2: =B14*B11*M3 -> 17.634822
A3: Linkedin | L3: TTT | M3: 1 | N3: maand
A4: Uitgenodigd | B4: 288
A5: Geaccepteerd | B5: 103 | C5: =B5/B4 -> 0.35763889
A6: Replies | B6: 70 | C6: =B6/B5 -> 0.67961165
A7: Demo's | B7: 19 | C7: =B7/B6 -> 0.27142857
A8: Klanten | B8: 4 | C8: =B8/B7 -> 0.21052632 | D8: Totale marge | E8: =B8*B12 -> 21796.64 | F8: Totale omzet | G8: ='Gem omzet bonai per maand'!D8*B8*12 -> 25643.2
A9: Gemiddelde omzet per klant per maand | B9: ='Gem omzet bonai per maand'!D8+49 -> 583.23333
A10: Gemiddelde omzet per klant per jaar | B10: =B9*12 -> 6998.8
A11: Gemiddelde marge per klant per maand | B11: ='Gem omzet bonai per maand'!H8+49 -> 454.09667
A12: Gemiddelde marge per klant per jaar | B12: =B11*12 -> 5449.16
A13: Uitnodiging naar klant per uitnodiging | B13: =B8/B4 -> 0.013888889
A14: Uitnodiging naar klant per acceptatie | B14: =B8/B5 -> 0.038834951
A16: Administratiekantoren #
A17: Zenvoices vs Basecone | C17: https://gemini.google.com/share/e0170f5ea437 | F17: https://www.perplexity.ai/search/hoeveel-administratie-en-accou-uw1Ib4wKSb6lEbFKnarM1g#1
A18: Zenvoices | B18: 100 | C18: tot | D18: 350 | E18: Administraties
A19: Basecone | B19: 2400 | C19: tot | D19: 5000 | E19: Administraties | F19: Informatie Basecone Patrick: | G19: 5000 kantoren | L19: Informatie Basecone website: 2400 kantoren
A20: 14-24 keer meer kantoren Basecone dan Zenvoices | B20: =AVERAGE(E20:G20) -> 19.142857 | C20: keer meer | E20: =D19/D18 -> 14.285714 | F20: tot | G20: =B19/B18 -> 24 | H20: keer meer
A21: Exact Online | B21: 0.5 | C21: % Scan & Herken
A22: Exact Online | B22: =B21*10000 -> 5000 | C22: https://www.perplexity.ai/search/hoeveel-administratie-en-accou-3yxVpHnnRwiCIaqQ_6MyVQ
A23: Exact meer dan Zenvoices | B23: =AVERAGE(E23:G23) -> 32.142857 | E23: =B22/D18 -> 14.285714 | F23: tot | G23: =B22/B18 -> 50 | H23: keer meer
A26: Salesfunnel Basecone | C26: =B29/400/2 -> 6.8914286 | D26: maanden voor outreach
A28: Linkedin
A29: Uitgenodigd | B29: =B4*B20 -> 5513.1429
A30: Geaccepteerd | B30: =B29*C30 -> 1971.7143 | C30: =C5 -> 0.35763889
A31: Replies | B31: =B30*C31 -> 1340 | C31: =C6 -> 0.67961165
A32: Demo's | B32: =B31*C32 -> 363.71429 | C32: =C7 -> 0.27142857 | E32: Marge | F32: Omzet Basecone | G32: Totaal omzet
A33: Klanten | B33: =B32*C33 -> 76.571429 | C33: =C8 -> 0.21052632 | D33: Waarde | E33: =B33*B37 -> 417249.97 | F33: =B33*'Gem omzet bonai per maand'!D8*12 -> 490884.11 | G33: =F33+G8 -> 516527.31
A34: Gemiddelde omzet per klant per maand | B34: ='Gem omzet bonai per maand'!D8+49 -> 583.23333
A35: Gemiddelde omzet per klant per jaar | B35: =B34*12 -> 6998.8
A36: Gemiddelde marge per klant per maand | B36: ='Gem omzet bonai per maand'!H8+49 -> 454.09667
A37: Gemiddelde marge per klant per jaar | B37: =B36*12 -> 5449.16
A38: Uitnodiging naar klant per uitnodiging | B38: =B33/B29 -> 0.013888889
A40: Salesfunnel Exact
A42: Linkedin
A43: Uitgenodigd | B43: =B23*B4 -> 9257.1429
A44: Geaccepteerd | B44: =B43*C44 -> 3310.7143 | C44: =C5 -> 0.35763889
A45: Replies | B45: =B44*C45 -> 2250 | C45: =C6 -> 0.67961165
A46: Demo's | B46: =B45*C46 -> 610.71429 | C46: =C7 -> 0.27142857 | E46: Marge | F46: Omzet Exact | G46: Totaal omzet
A47: Klanten | B47: =B46*C47 -> 128.57143 | C47: =C8 -> 0.21052632 | D47: Waarde | E47: =B47*B51 -> 700606.29 | F47: =B47*'Gem omzet bonai per maand'!D8*12 -> 824245.71 | G47: =F47+G24 -> 824245.71
A48: Gemiddelde omzet per klant per maand | B48: ='Gem omzet bonai per maand'!D8+49 -> 583.23333
A49: Gemiddelde omzet per klant per jaar | B49: =B48*12 -> 6998.8
A50: Gemiddelde marge per klant per maand | B50: ='Gem omzet bonai per maand'!H8+49 -> 454.09667
A51: Gemiddelde marge per klant per jaar | B51: =B50*12 -> 5449.16
A52: Uitnodiging naar klant per uitnodiging | B52: =B47/B43 -> 0.013888889
A54: Totaal aantal klanten | B54: =B33+B8+B47 -> 209.14286
A55: Na 0.5 - 1 jaar
A56: Marge Basecone | B56: =E33+E8 -> 439046.61 | C56: per jaar
A57: Marge Exact | B57: =E47 -> 700606.29 | C57: per jaar
A58: Marge Basecone+Exact | B58: =B57+B56 -> 1139652.9
A59: Waarderings Multiple | B59: 4 | C59: https://gemini.google.com/share/489a5b822c07
A60: Waardering bedrijf ENKEL BASECONE | B60: =B59*B56 -> 1756186.4
A61: Waardering bedrijf ENKEL EXACT | B61: =B57*B59 -> 2802425.1
A62: Waarderin bedrijf Basecone + Exact | B62: =B60+B61 -> 4558611.6
A65: Bonai Full product
A66: Bereidheid te betalen klanten voor Zenvoices + Procai per jaar | B66: =15000+B12 -> 20449.16 | C66: Marge | D66: =B66-'Gem omzet bonai per maand'!G8*12 -> 18899.52
A67: Overstappen naar Bonai Full service | B67: 0.1 | C67: Aanname
A68: Overstap tijd | B68: 6 | C68: maanden
A69: Aantal klanten na overstaptijd | B69: =B67*B54 -> 20.914286
A70: Omzet Bonai full service per jaar | B70: =B66*B69 -> 427679.57 | C70: Marge | D70: =D66*B69 -> 395269.96
A72: Totaal omzet na 1 - 1.5 jaar | B72: =B70+(B54-B69)*B35 -> 1745053.7 | C72: Marge | D72: =D70+(B54-B69)*B37 -> 1420957.6
A73: Waardering bedrijf | B73: =B74*B72 -> 11342849
A74: Waarderings Multiple | B74: 6.5 | C74: https://gemini.google.com/share/6930ff7bd190
A75: Toevoeging iedere extra klant: | B75: =B66 -> 20449.16 | C75: omzet
B76: =D66 -> 18899.52 | C76: marge
B77: =B75*B74 -> 132919.54 | C77: Waardering

Sheet Gem omzet bonai per maand
A1: Maand | B1: Klant | C1: Bonnen | D1: Variabele omzet | E1: Variabele kosten | F1: Hosting | G1: Totale kosten | H1: Marge
A2: Dec | B2: Jacc | C2: 829 | D2: =829*0.4 -> 331.6 | E2: =C2*0.07 -> 58.03 | F2: 25 | G2: =E2+F2 -> 83.03 | H2: =D2-G2 -> 248.57
A3: Jan | B3: Jacc | C3: 1074 | D3: =400+(74*0.3) -> 422.2 | E3: =C3*0.07 -> 75.18 | F3: 25 | G3: =E3+F3 -> 100.18 | H3: =D3-G3 -> 322.02
A4: Feb | B4: Jacc | C4: 1566 | D4: =400+(566*0.3) -> 569.8 | E4: =C4*0.07 -> 109.62 | F4: 25 | G4: =E4+F4 -> 134.62 | H4: =D4-G4 -> 435.18
A5: Dec | B5: CS | C5: 1092 | D5: =400+(92*0.3) -> 427.6 | E5: =C5*0.07 -> 76.44 | F5: 25 | G5: =E5+F5 -> 101.44 | H5: =D5-G5 -> 326.16
A6: Jan | B6: CS | C6: 3459 | D6: =1000+(459*0.2) -> 1091.8 | E6: =C6*0.07 -> 242.13 | F6: 25 | G6: =E6+F6 -> 267.13 | H6: =D6-G6 -> 824.67
A7: Feb | B7: CS | C7: 906 | D7: =906*0.4 -> 362.4 | E7: =C7*0.07 -> 63.42 | F7: 25 | G7: =E7+F7 -> 88.42 | H7: =D7-G7 -> 273.98
A8: GEMIDDELD | C8: =AVERAGE(C2:C7) -> 1487.6667 | D8: =AVERAGE(D2:D7) -> 534.23333 | E8: =AVERAGE(E2:E7) -> 104.13667 | F8: =AVERAGE(F2:F7) -> 25 | G8: =AVERAGE(G2:G7) -> 129.13667 | H8: =AVERAGE(H2:H7) -> 405.09667
